MANIFEST.in
README.rst
setup.py
fxos_appgen/__init__.py
fxos_appgen/app_install.js
fxos_appgen/generator.py
fxos_appgen.egg-info/PKG-INFO
fxos_appgen.egg-info/SOURCES.txt
fxos_appgen.egg-info/dependency_links.txt
fxos_appgen.egg-info/entry_points.txt
fxos_appgen.egg-info/not-zip-safe
fxos_appgen.egg-info/requires.txt
fxos_appgen.egg-info/top_level.txt
fxos_appgen/resources/extract_permissions.js
fxos_appgen/resources/index.html
fxos_appgen/resources/1.3/complete_permissions.json
fxos_appgen/resources/1.3/manifest.webapp
fxos_appgen/resources/1.3/messages.json
fxos_appgen/resources/1.4/complete_permissions.json
fxos_appgen/resources/1.4/manifest.webapp
fxos_appgen/resources/1.4/messages.json
fxos_appgen/resources/2.0/complete_permissions.json
fxos_appgen/resources/2.0/manifest.webapp
fxos_appgen/resources/2.0/messages.json
fxos_appgen/resources/2.1/complete_permissions.json
fxos_appgen/resources/2.1/manifest.webapp
fxos_appgen/resources/2.1/messages.json
fxos_appgen/resources/2.2/complete_permissions.json
fxos_appgen/resources/2.2/manifest.webapp
fxos_appgen/resources/2.2/messages.json
fxos_appgen/resources/2.5/complete_permissions.json
fxos_appgen/resources/2.5/manifest.webapp
fxos_appgen/resources/2.5/messages.json