Metadata-Version: 1.0
Name: fxos-appgen
Version: 0.15
Summary: Generates and installs FxOS apps
Home-page: https://github.com/mozilla-b2g/fxos-certsuite
Author: Mozilla Automation and Testing Team
Author-email: tools@lists.mozilla.org
License: MPL
Keywords: mozilla
Platform: UNKNOWN
